{
  "generatedAt": "2026-03-16T09:04:21.898Z",
  "compressedChunkCount": 66,
  "publicBlogCount": 142,
  "blogDataBrotliBudgetKb": 241,
  "checks": [
    {
      "label": "index JS (brotli)",
      "file": "index-BNRXXYKA.js.br",
      "sizeKb": 13.64,
      "maxKb": 15
    },
    {
      "label": "vendor-react JS (brotli)",
      "file": "vendor-react-D-tFKdcd.js.br",
      "sizeKb": 54,
      "maxKb": 58
    },
    {
      "label": "vendor-router JS (brotli)",
      "file": "vendor-router-WzOq1lTH.js.br",
      "sizeKb": 10.67,
      "maxKb": 24
    },
    {
      "label": "vendor-motion JS (brotli)",
      "file": "vendor-motion-INGeV9gw.js.br",
      "sizeKb": 33.97,
      "maxKb": 36
    },
    {
      "label": "blogData JS (brotli)",
      "file": "blogData-kAHgXY65.js.br",
      "sizeKb": 179.99,
      "maxKb": 241
    },
    {
      "label": "main CSS (brotli)",
      "file": "index-Clg_k4H4.css.br",
      "sizeKb": 13.65,
      "maxKb": 15
    }
  ],
  "issueCount": 0,
  "issues": []
}